README.rst
setup.cfg
setup.py
fuzzyio/__init__.py
fuzzyio/agent.py
fuzzyio/evaluation.py
fuzzyio/feedback.py
fuzzyio/server.py
fuzzyio.egg-info/PKG-INFO
fuzzyio.egg-info/SOURCES.txt
fuzzyio.egg-info/dependency_links.txt
fuzzyio.egg-info/not-zip-safe
fuzzyio.egg-info/requires.txt
fuzzyio.egg-info/top_level.txt
fuzzyio/errors/__init__.py
fuzzyio/errors/deleted_agent.py
fuzzyio/errors/http.py
fuzzyio/errors/no_such_agent.py