Metadata-Version: 1.0
Name: fuzzyio
Version: 0.2.0.dev0
Summary: fuzzy.io API
Home-page: https://github.com/fuzzy-io/python
Author: Evan Prodromou
Author-email: evan@fuzzy.io
License: Apache 2.0
Platform: UNKNOWN
